omnik/__init__.py
omnik/client.py
omnik/datalogger.py
omnik/plugins/__init__.py
omnik/plugins/influxdb.py
omnik/plugins/pvoutput.py
omnik_data_logger-0.1.1.data/scripts/omnik-logger
omnik_data_logger-0.1.1.dist-info/LICENSE.txt
omnik_data_logger-0.1.1.dist-info/METADATA
omnik_data_logger-0.1.1.dist-info/WHEEL
omnik_data_logger-0.1.1.dist-info/top_level.txt
omnik_data_logger-0.1.1.dist-info/RECORD
