Metadata-Version: 2.1
Name: omnik-data-logger
Version: 0.1.1
Summary: Omnik Data Logger
Home-page: https://github.com/paprins/omnik-data-logger
Author: Pascal Prins
Author-email: pascal.prins@foobar-it.com
License: gpl-3.0
Platform: UNKNOWN
Classifier: Development Status :: 4 - Beta
Classifier: Topic :: Home Automation
Classifier: Programming Language :: Python :: 3.7
Classifier: License :: OSI Approved :: GNU General Public License v3 (GPLv3)
Classifier: Operating System :: OS Independent
Requires-Dist: configparser (>=3.7.4)
Requires-Dist: requests (>=2.21.0)
Requires-Dist: cachetools (>=3.1.1)
Requires-Dist: pytz (==2019.1)
